MANIFEST.in
README.md
setup.cfg
setup.py
docs/License.txt
docs/authors.rst
docs/release-notes.rst
redis_py_cluster_gcom.egg-info/PKG-INFO
redis_py_cluster_gcom.egg-info/SOURCES.txt
redis_py_cluster_gcom.egg-info/dependency_links.txt
redis_py_cluster_gcom.egg-info/requires.txt
redis_py_cluster_gcom.egg-info/top_level.txt
rediscluster/__init__.py
rediscluster/client.py
rediscluster/connection.py
rediscluster/crc.py
rediscluster/exceptions.py
rediscluster/nodemanager.py
rediscluster/pipeline.py
rediscluster/pubsub.py
rediscluster/utils.py